kotpy/__init__.py
kotpy/collections.py
kotpy-0.0.1.dist-info/METADATA
kotpy-0.0.1.dist-info/WHEEL
kotpy-0.0.1.dist-info/top_level.txt
kotpy-0.0.1.dist-info/RECORD
